[
    {
        "line": "42",
        "column": "3",
        "severity": "error",
        "message": "Redundant 'public' modifier.",
        "source": "com.puppycrawl.tools.checkstyle.checks.modifier.RedundantModifierCheck"
    },
    {
        "line": "51",
        "column": "3",
        "severity": "error",
        "message": "Redundant 'public' modifier.",
        "source": "com.puppycrawl.tools.checkstyle.checks.modifier.RedundantModifierCheck"
    },
    {
        "line": "59",
        "column": "3",
        "severity": "error",
        "message": "Redundant 'public' modifier.",
        "source": "com.puppycrawl.tools.checkstyle.checks.modifier.RedundantModifierCheck"
    },
    {
        "line": "65",
        "column": "3",
        "severity": "error",
        "message": "Redundant 'public' modifier.",
        "source": "com.puppycrawl.tools.checkstyle.checks.modifier.RedundantModifierCheck"
    },
    {
        "line": "69",
        "column": "3",
        "severity": "error",
        "message": "Redundant 'public' modifier.",
        "source": "com.puppycrawl.tools.checkstyle.checks.modifier.RedundantModifierCheck"
    },
    {
        "line": "73",
        "column": "3",
        "severity": "error",
        "message": "Redundant 'public' modifier.",
        "source": "com.puppycrawl.tools.checkstyle.checks.modifier.RedundantModifierCheck"
    }
]