[
    {
        "line": "22",
        "column": "8",
        "severity": "error",
        "message": "Unused import - org.apache.hadoop.util.VersionInfo.",
        "source": "com.puppycrawl.tools.checkstyle.checks.imports.UnusedImportsCheck"
    },
    {
        "line": "24",
        "column": "8",
        "severity": "error",
        "message": "Unused import - org.apache.hadoop.yarn.util.YarnVersionInfo.",
        "source": "com.puppycrawl.tools.checkstyle.checks.imports.UnusedImportsCheck"
    },
    {
        "line": "41",
        "column": "79",
        "severity": "error",
        "message": "'+' should be on a new line.",
        "source": "com.puppycrawl.tools.checkstyle.checks.whitespace.OperatorWrapCheck"
    },
    {
        "line": "43",
        "column": "61",
        "severity": "error",
        "message": "'+' should be on a new line.",
        "source": "com.puppycrawl.tools.checkstyle.checks.whitespace.OperatorWrapCheck"
    }
]