[
    {
        "line": "24",
        "column": "8",
        "severity": "error",
        "message": "Unused import - java.net.InetAddress.",
        "source": "com.puppycrawl.tools.checkstyle.checks.imports.UnusedImportsCheck"
    },
    {
        "line": "26",
        "column": "8",
        "severity": "error",
        "message": "Unused import - java.net.SocketAddress.",
        "source": "com.puppycrawl.tools.checkstyle.checks.imports.UnusedImportsCheck"
    },
    {
        "line": "34",
        "column": "1",
        "severity": "error",
        "message": "Redundant import from the same package - org.apache.hadoop.hdfs.nfs.nfs3.Nfs3.",
        "source": "com.puppycrawl.tools.checkstyle.checks.imports.RedundantImportCheck"
    },
    {
        "line": "35",
        "column": "1",
        "severity": "error",
        "message": "Redundant import from the same package - org.apache.hadoop.hdfs.nfs.nfs3.RpcProgramNfs3.",
        "source": "com.puppycrawl.tools.checkstyle.checks.imports.RedundantImportCheck"
    },
    {
        "line": "43",
        "column": "8",
        "severity": "error",
        "message": "Unused import - org.apache.hadoop.oncrpc.RpcInfo.",
        "source": "com.puppycrawl.tools.checkstyle.checks.imports.UnusedImportsCheck"
    },
    {
        "line": "44",
        "column": "8",
        "severity": "error",
        "message": "Unused import - org.apache.hadoop.oncrpc.RpcMessage.",
        "source": "com.puppycrawl.tools.checkstyle.checks.imports.UnusedImportsCheck"
    },
    {
        "line": "49",
        "column": "8",
        "severity": "error",
        "message": "Unused import - org.jboss.netty.buffer.ChannelBuffer.",
        "source": "com.puppycrawl.tools.checkstyle.checks.imports.UnusedImportsCheck"
    },
    {
        "line": "50",
        "column": "8",
        "severity": "error",
        "message": "Unused import - org.jboss.netty.channel.Channel.",
        "source": "com.puppycrawl.tools.checkstyle.checks.imports.UnusedImportsCheck"
    },
    {
        "line": "51",
        "column": "8",
        "severity": "error",
        "message": "Unused import - org.jboss.netty.channel.ChannelHandlerContext.",
        "source": "com.puppycrawl.tools.checkstyle.checks.imports.UnusedImportsCheck"
    },
    {
        "line": "63",
        "column": "27",
        "severity": "error",
        "message": "Variable 'config' must be private and have accessor methods.",
        "source": "com.puppycrawl.tools.checkstyle.checks.design.VisibilityModifierCheck"
    },
    {
        "line": "64",
        "column": "25",
        "severity": "error",
        "message": "Variable 'cluster' must be private and have accessor methods.",
        "source": "com.puppycrawl.tools.checkstyle.checks.design.VisibilityModifierCheck"
    },
    {
        "line": "65",
        "column": "32",
        "severity": "error",
        "message": "Variable 'hdfs' must be private and have accessor methods.",
        "source": "com.puppycrawl.tools.checkstyle.checks.design.VisibilityModifierCheck"
    },
    {
        "line": "66",
        "column": "19",
        "severity": "error",
        "message": "Variable 'nn' must be private and have accessor methods.",
        "source": "com.puppycrawl.tools.checkstyle.checks.design.VisibilityModifierCheck"
    },
    {
        "line": "67",
        "column": "25",
        "severity": "error",
        "message": "Variable 'nfsd' must be private and have accessor methods.",
        "source": "com.puppycrawl.tools.checkstyle.checks.design.VisibilityModifierCheck"
    },
    {
        "line": "68",
        "column": "17",
        "severity": "error",
        "message": "Variable 'testdir' must be private and have accessor methods.",
        "source": "com.puppycrawl.tools.checkstyle.checks.design.VisibilityModifierCheck"
    },
    {
        "line": "69",
        "column": "26",
        "severity": "error",
        "message": "Variable 'securityHandler' must be private and have accessor methods.",
        "source": "com.puppycrawl.tools.checkstyle.checks.design.VisibilityModifierCheck"
    },
    {
        "line": "124",
        "column": "9",
        "severity": "error",
        "message": "Name 'xdr_req' must match pattern '^[a-z][a-zA-Z0-9]*$'.",
        "source": "com.puppycrawl.tools.checkstyle.checks.naming.LocalVariableNameCheck"
    },
    {
        "line": "129",
        "column": "22",
        "severity": "error",
        "message": "'100' is a magic number.",
        "source": "com.puppycrawl.tools.checkstyle.checks.coding.MagicNumberCheck"
    },
    {
        "line": "132",
        "column": "61",
        "severity": "error",
        "message": "'1234' is a magic number.",
        "source": "com.puppycrawl.tools.checkstyle.checks.coding.MagicNumberCheck"
    },
    {
        "line": "146",
        "column": "22",
        "severity": "error",
        "message": "'100' is a magic number.",
        "source": "com.puppycrawl.tools.checkstyle.checks.coding.MagicNumberCheck"
    },
    {
        "line": "149",
        "column": "44",
        "severity": "error",
        "message": "'1234' is a magic number.",
        "source": "com.puppycrawl.tools.checkstyle.checks.coding.MagicNumberCheck"
    },
    {
        "line": "159",
        "column": "44",
        "severity": "error",
        "message": "'1234' is a magic number.",
        "source": "com.puppycrawl.tools.checkstyle.checks.coding.MagicNumberCheck"
    },
    {
        "line": "172",
        "column": "9",
        "severity": "error",
        "message": "Name 'xdr_req' must match pattern '^[a-z][a-zA-Z0-9]*$'.",
        "source": "com.puppycrawl.tools.checkstyle.checks.naming.LocalVariableNameCheck"
    },
    {
        "line": "177",
        "column": "22",
        "severity": "error",
        "message": "'100' is a magic number.",
        "source": "com.puppycrawl.tools.checkstyle.checks.coding.MagicNumberCheck"
    },
    {
        "line": "182",
        "column": "9",
        "severity": "error",
        "message": "'1234' is a magic number.",
        "source": "com.puppycrawl.tools.checkstyle.checks.coding.MagicNumberCheck"
    },
    {
        "line": "196",
        "column": "22",
        "severity": "error",
        "message": "'100' is a magic number.",
        "source": "com.puppycrawl.tools.checkstyle.checks.coding.MagicNumberCheck"
    },
    {
        "line": "200",
        "column": "44",
        "severity": "error",
        "message": "'1234' is a magic number.",
        "source": "com.puppycrawl.tools.checkstyle.checks.coding.MagicNumberCheck"
    },
    {
        "line": "210",
        "column": "44",
        "severity": "error",
        "message": "'1234' is a magic number.",
        "source": "com.puppycrawl.tools.checkstyle.checks.coding.MagicNumberCheck"
    }
]