[
    {
        "line": "3",
        "severity": "error",
        "message": "Line has trailing spaces.",
        "source": "com.puppycrawl.tools.checkstyle.checks.regexp.RegexpSinglelineCheck"
    },
    {
        "line": "7",
        "severity": "error",
        "message": "Line has trailing spaces.",
        "source": "com.puppycrawl.tools.checkstyle.checks.regexp.RegexpSinglelineCheck"
    },
    {
        "line": "9",
        "severity": "error",
        "message": "Line has trailing spaces.",
        "source": "com.puppycrawl.tools.checkstyle.checks.regexp.RegexpSinglelineCheck"
    },
    {
        "line": "22",
        "severity": "error",
        "message": "Line has trailing spaces.",
        "source": "com.puppycrawl.tools.checkstyle.checks.regexp.RegexpSinglelineCheck"
    },
    {
        "line": "32",
        "column": "33",
        "severity": "error",
        "message": "Use a single space to separate non-whitespace characters.",
        "source": "com.puppycrawl.tools.checkstyle.checks.whitespace.SingleSpaceSeparatorCheck"
    },
    {
        "line": "45",
        "severity": "error",
        "message": "Line has trailing spaces.",
        "source": "com.puppycrawl.tools.checkstyle.checks.regexp.RegexpSinglelineCheck"
    },
    {
        "line": "88",
        "severity": "error",
        "message": "Line has trailing spaces.",
        "source": "com.puppycrawl.tools.checkstyle.checks.regexp.RegexpSinglelineCheck"
    }
]