[
    {
        "line": "50",
        "severity": "error",
        "message": "Line has trailing spaces.",
        "source": "com.puppycrawl.tools.checkstyle.checks.regexp.RegexpSinglelineCheck"
    },
    {
        "line": "51",
        "column": "3",
        "severity": "error",
        "message": "Missing a Javadoc comment.",
        "source": "com.puppycrawl.tools.checkstyle.checks.javadoc.JavadocVariableCheck"
    },
    {
        "line": "52",
        "severity": "error",
        "message": "Line has trailing spaces.",
        "source": "com.puppycrawl.tools.checkstyle.checks.regexp.RegexpSinglelineCheck"
    },
    {
        "line": "59",
        "severity": "error",
        "message": "Line has trailing spaces.",
        "source": "com.puppycrawl.tools.checkstyle.checks.regexp.RegexpSinglelineCheck"
    },
    {
        "line": "69",
        "severity": "error",
        "message": "Line has trailing spaces.",
        "source": "com.puppycrawl.tools.checkstyle.checks.regexp.RegexpSinglelineCheck"
    },
    {
        "line": "80",
        "severity": "error",
        "message": "Line has trailing spaces.",
        "source": "com.puppycrawl.tools.checkstyle.checks.regexp.RegexpSinglelineCheck"
    },
    {
        "line": "92",
        "severity": "error",
        "message": "Line has trailing spaces.",
        "source": "com.puppycrawl.tools.checkstyle.checks.regexp.RegexpSinglelineCheck"
    },
    {
        "line": "104",
        "severity": "error",
        "message": "Line has trailing spaces.",
        "source": "com.puppycrawl.tools.checkstyle.checks.regexp.RegexpSinglelineCheck"
    },
    {
        "line": "108",
        "severity": "error",
        "message": "Line has trailing spaces.",
        "source": "com.puppycrawl.tools.checkstyle.checks.regexp.RegexpSinglelineCheck"
    },
    {
        "line": "119",
        "severity": "error",
        "message": "Line has trailing spaces.",
        "source": "com.puppycrawl.tools.checkstyle.checks.regexp.RegexpSinglelineCheck"
    },
    {
        "line": "127",
        "severity": "error",
        "message": "Line has trailing spaces.",
        "source": "com.puppycrawl.tools.checkstyle.checks.regexp.RegexpSinglelineCheck"
    },
    {
        "line": "134",
        "severity": "error",
        "message": "Line has trailing spaces.",
        "source": "com.puppycrawl.tools.checkstyle.checks.regexp.RegexpSinglelineCheck"
    },
    {
        "line": "140",
        "severity": "error",
        "message": "Line has trailing spaces.",
        "source": "com.puppycrawl.tools.checkstyle.checks.regexp.RegexpSinglelineCheck"
    },
    {
        "line": "148",
        "severity": "error",
        "message": "Line has trailing spaces.",
        "source": "com.puppycrawl.tools.checkstyle.checks.regexp.RegexpSinglelineCheck"
    },
    {
        "line": "154",
        "severity": "error",
        "message": "Line has trailing spaces.",
        "source": "com.puppycrawl.tools.checkstyle.checks.regexp.RegexpSinglelineCheck"
    },
    {
        "line": "159",
        "severity": "error",
        "message": "Line has trailing spaces.",
        "source": "com.puppycrawl.tools.checkstyle.checks.regexp.RegexpSinglelineCheck"
    },
    {
        "line": "167",
        "severity": "error",
        "message": "Line has trailing spaces.",
        "source": "com.puppycrawl.tools.checkstyle.checks.regexp.RegexpSinglelineCheck"
    },
    {
        "line": "179",
        "severity": "error",
        "message": "Line has trailing spaces.",
        "source": "com.puppycrawl.tools.checkstyle.checks.regexp.RegexpSinglelineCheck"
    },
    {
        "line": "191",
        "severity": "error",
        "message": "Line has trailing spaces.",
        "source": "com.puppycrawl.tools.checkstyle.checks.regexp.RegexpSinglelineCheck"
    },
    {
        "line": "195",
        "severity": "error",
        "message": "Line has trailing spaces.",
        "source": "com.puppycrawl.tools.checkstyle.checks.regexp.RegexpSinglelineCheck"
    },
    {
        "line": "196",
        "severity": "error",
        "message": "Line has trailing spaces.",
        "source": "com.puppycrawl.tools.checkstyle.checks.regexp.RegexpSinglelineCheck"
    },
    {
        "line": "198",
        "severity": "error",
        "message": "Line has trailing spaces.",
        "source": "com.puppycrawl.tools.checkstyle.checks.regexp.RegexpSinglelineCheck"
    },
    {
        "line": "208",
        "severity": "error",
        "message": "Line has trailing spaces.",
        "source": "com.puppycrawl.tools.checkstyle.checks.regexp.RegexpSinglelineCheck"
    },
    {
        "line": "221",
        "severity": "error",
        "message": "Line has trailing spaces.",
        "source": "com.puppycrawl.tools.checkstyle.checks.regexp.RegexpSinglelineCheck"
    },
    {
        "line": "225",
        "severity": "error",
        "message": "Line has trailing spaces.",
        "source": "com.puppycrawl.tools.checkstyle.checks.regexp.RegexpSinglelineCheck"
    },
    {
        "line": "230",
        "severity": "error",
        "message": "Line has trailing spaces.",
        "source": "com.puppycrawl.tools.checkstyle.checks.regexp.RegexpSinglelineCheck"
    },
    {
        "line": "239",
        "severity": "error",
        "message": "Line has trailing spaces.",
        "source": "com.puppycrawl.tools.checkstyle.checks.regexp.RegexpSinglelineCheck"
    },
    {
        "line": "240",
        "severity": "error",
        "message": "Line has trailing spaces.",
        "source": "com.puppycrawl.tools.checkstyle.checks.regexp.RegexpSinglelineCheck"
    },
    {
        "line": "243",
        "severity": "error",
        "message": "Line has trailing spaces.",
        "source": "com.puppycrawl.tools.checkstyle.checks.regexp.RegexpSinglelineCheck"
    },
    {
        "line": "249",
        "severity": "error",
        "message": "Line has trailing spaces.",
        "source": "com.puppycrawl.tools.checkstyle.checks.regexp.RegexpSinglelineCheck"
    },
    {
        "line": "252",
        "severity": "error",
        "message": "Line is longer than 200 characters (found 248).",
        "source": "com.puppycrawl.tools.checkstyle.checks.sizes.LineLengthCheck"
    },
    {
        "line": "257",
        "severity": "error",
        "message": "Line has trailing spaces.",
        "source": "com.puppycrawl.tools.checkstyle.checks.regexp.RegexpSinglelineCheck"
    },
    {
        "line": "258",
        "severity": "error",
        "message": "Line is longer than 200 characters (found 229).",
        "source": "com.puppycrawl.tools.checkstyle.checks.sizes.LineLengthCheck"
    },
    {
        "line": "259",
        "severity": "error",
        "message": "Line has trailing spaces.",
        "source": "com.puppycrawl.tools.checkstyle.checks.regexp.RegexpSinglelineCheck"
    },
    {
        "line": "266",
        "severity": "error",
        "message": "Line has trailing spaces.",
        "source": "com.puppycrawl.tools.checkstyle.checks.regexp.RegexpSinglelineCheck"
    },
    {
        "line": "270",
        "severity": "error",
        "message": "Line has trailing spaces.",
        "source": "com.puppycrawl.tools.checkstyle.checks.regexp.RegexpSinglelineCheck"
    },
    {
        "line": "275",
        "severity": "error",
        "message": "Line has trailing spaces.",
        "source": "com.puppycrawl.tools.checkstyle.checks.regexp.RegexpSinglelineCheck"
    },
    {
        "line": "277",
        "severity": "error",
        "message": "Line is longer than 200 characters (found 210).",
        "source": "com.puppycrawl.tools.checkstyle.checks.sizes.LineLengthCheck"
    },
    {
        "line": "283",
        "severity": "error",
        "message": "Line has trailing spaces.",
        "source": "com.puppycrawl.tools.checkstyle.checks.regexp.RegexpSinglelineCheck"
    },
    {
        "line": "286",
        "severity": "error",
        "message": "Line is longer than 200 characters (found 287).",
        "source": "com.puppycrawl.tools.checkstyle.checks.sizes.LineLengthCheck"
    },
    {
        "line": "295",
        "severity": "error",
        "message": "Line has trailing spaces.",
        "source": "com.puppycrawl.tools.checkstyle.checks.regexp.RegexpSinglelineCheck"
    },
    {
        "line": "298",
        "severity": "error",
        "message": "Line has trailing spaces.",
        "source": "com.puppycrawl.tools.checkstyle.checks.regexp.RegexpSinglelineCheck"
    },
    {
        "line": "300",
        "severity": "error",
        "message": "Line is longer than 200 characters (found 207).",
        "source": "com.puppycrawl.tools.checkstyle.checks.sizes.LineLengthCheck"
    },
    {
        "line": "302",
        "severity": "error",
        "message": "Line has trailing spaces.",
        "source": "com.puppycrawl.tools.checkstyle.checks.regexp.RegexpSinglelineCheck"
    },
    {
        "line": "303",
        "severity": "error",
        "message": "Line is longer than 200 characters (found 237).",
        "source": "com.puppycrawl.tools.checkstyle.checks.sizes.LineLengthCheck"
    },
    {
        "line": "305",
        "severity": "error",
        "message": "Line has trailing spaces.",
        "source": "com.puppycrawl.tools.checkstyle.checks.regexp.RegexpSinglelineCheck"
    },
    {
        "line": "306",
        "severity": "error",
        "message": "Line is longer than 200 characters (found 283).",
        "source": "com.puppycrawl.tools.checkstyle.checks.sizes.LineLengthCheck"
    },
    {
        "line": "309",
        "severity": "error",
        "message": "Line has trailing spaces.",
        "source": "com.puppycrawl.tools.checkstyle.checks.regexp.RegexpSinglelineCheck"
    },
    {
        "line": "310",
        "severity": "error",
        "message": "Line has trailing spaces.",
        "source": "com.puppycrawl.tools.checkstyle.checks.regexp.RegexpSinglelineCheck"
    },
    {
        "line": "314",
        "severity": "error",
        "message": "Line has trailing spaces.",
        "source": "com.puppycrawl.tools.checkstyle.checks.regexp.RegexpSinglelineCheck"
    },
    {
        "line": "318",
        "severity": "error",
        "message": "Line has trailing spaces.",
        "source": "com.puppycrawl.tools.checkstyle.checks.regexp.RegexpSinglelineCheck"
    },
    {
        "line": "322",
        "severity": "error",
        "message": "Line has trailing spaces.",
        "source": "com.puppycrawl.tools.checkstyle.checks.regexp.RegexpSinglelineCheck"
    },
    {
        "line": "331",
        "severity": "error",
        "message": "Line is longer than 200 characters (found 221).",
        "source": "com.puppycrawl.tools.checkstyle.checks.sizes.LineLengthCheck"
    },
    {
        "line": "332",
        "severity": "error",
        "message": "Line has trailing spaces.",
        "source": "com.puppycrawl.tools.checkstyle.checks.regexp.RegexpSinglelineCheck"
    },
    {
        "line": "334",
        "severity": "error",
        "message": "Line has trailing spaces.",
        "source": "com.puppycrawl.tools.checkstyle.checks.regexp.RegexpSinglelineCheck"
    },
    {
        "line": "335",
        "severity": "error",
        "message": "Line has trailing spaces.",
        "source": "com.puppycrawl.tools.checkstyle.checks.regexp.RegexpSinglelineCheck"
    },
    {
        "line": "340",
        "severity": "error",
        "message": "Line has trailing spaces.",
        "source": "com.puppycrawl.tools.checkstyle.checks.regexp.RegexpSinglelineCheck"
    },
    {
        "line": "344",
        "severity": "error",
        "message": "Line has trailing spaces.",
        "source": "com.puppycrawl.tools.checkstyle.checks.regexp.RegexpSinglelineCheck"
    },
    {
        "line": "346",
        "severity": "error",
        "message": "Line has trailing spaces.",
        "source": "com.puppycrawl.tools.checkstyle.checks.regexp.RegexpSinglelineCheck"
    },
    {
        "line": "355",
        "severity": "error",
        "message": "Line has trailing spaces.",
        "source": "com.puppycrawl.tools.checkstyle.checks.regexp.RegexpSinglelineCheck"
    },
    {
        "line": "356",
        "severity": "error",
        "message": "Line has trailing spaces.",
        "source": "com.puppycrawl.tools.checkstyle.checks.regexp.RegexpSinglelineCheck"
    },
    {
        "line": "358",
        "severity": "error",
        "message": "Line has trailing spaces.",
        "source": "com.puppycrawl.tools.checkstyle.checks.regexp.RegexpSinglelineCheck"
    },
    {
        "line": "360",
        "severity": "error",
        "message": "Line has trailing spaces.",
        "source": "com.puppycrawl.tools.checkstyle.checks.regexp.RegexpSinglelineCheck"
    },
    {
        "line": "367",
        "severity": "error",
        "message": "Line has trailing spaces.",
        "source": "com.puppycrawl.tools.checkstyle.checks.regexp.RegexpSinglelineCheck"
    },
    {
        "line": "371",
        "severity": "error",
        "message": "Line has trailing spaces.",
        "source": "com.puppycrawl.tools.checkstyle.checks.regexp.RegexpSinglelineCheck"
    },
    {
        "line": "383",
        "severity": "error",
        "message": "Line has trailing spaces.",
        "source": "com.puppycrawl.tools.checkstyle.checks.regexp.RegexpSinglelineCheck"
    },
    {
        "line": "387",
        "severity": "error",
        "message": "Line has trailing spaces.",
        "source": "com.puppycrawl.tools.checkstyle.checks.regexp.RegexpSinglelineCheck"
    },
    {
        "line": "389",
        "severity": "error",
        "message": "Line has trailing spaces.",
        "source": "com.puppycrawl.tools.checkstyle.checks.regexp.RegexpSinglelineCheck"
    },
    {
        "line": "392",
        "severity": "error",
        "message": "Line has trailing spaces.",
        "source": "com.puppycrawl.tools.checkstyle.checks.regexp.RegexpSinglelineCheck"
    },
    {
        "line": "395",
        "severity": "error",
        "message": "Line has trailing spaces.",
        "source": "com.puppycrawl.tools.checkstyle.checks.regexp.RegexpSinglelineCheck"
    },
    {
        "line": "401",
        "severity": "error",
        "message": "Line has trailing spaces.",
        "source": "com.puppycrawl.tools.checkstyle.checks.regexp.RegexpSinglelineCheck"
    },
    {
        "line": "406",
        "severity": "error",
        "message": "Line has trailing spaces.",
        "source": "com.puppycrawl.tools.checkstyle.checks.regexp.RegexpSinglelineCheck"
    },
    {
        "line": "408",
        "severity": "error",
        "message": "Line has trailing spaces.",
        "source": "com.puppycrawl.tools.checkstyle.checks.regexp.RegexpSinglelineCheck"
    },
    {
        "line": "412",
        "severity": "error",
        "message": "Line has trailing spaces.",
        "source": "com.puppycrawl.tools.checkstyle.checks.regexp.RegexpSinglelineCheck"
    },
    {
        "line": "415",
        "severity": "error",
        "message": "Line has trailing spaces.",
        "source": "com.puppycrawl.tools.checkstyle.checks.regexp.RegexpSinglelineCheck"
    },
    {
        "line": "427",
        "severity": "error",
        "message": "Line has trailing spaces.",
        "source": "com.puppycrawl.tools.checkstyle.checks.regexp.RegexpSinglelineCheck"
    },
    {
        "line": "429",
        "severity": "error",
        "message": "Line has trailing spaces.",
        "source": "com.puppycrawl.tools.checkstyle.checks.regexp.RegexpSinglelineCheck"
    },
    {
        "line": "439",
        "severity": "error",
        "message": "Line has trailing spaces.",
        "source": "com.puppycrawl.tools.checkstyle.checks.regexp.RegexpSinglelineCheck"
    },
    {
        "line": "442",
        "severity": "error",
        "message": "Line has trailing spaces.",
        "source": "com.puppycrawl.tools.checkstyle.checks.regexp.RegexpSinglelineCheck"
    },
    {
        "line": "445",
        "severity": "error",
        "message": "Line has trailing spaces.",
        "source": "com.puppycrawl.tools.checkstyle.checks.regexp.RegexpSinglelineCheck"
    },
    {
        "line": "455",
        "severity": "error",
        "message": "Line has trailing spaces.",
        "source": "com.puppycrawl.tools.checkstyle.checks.regexp.RegexpSinglelineCheck"
    },
    {
        "line": "461",
        "severity": "error",
        "message": "Line has trailing spaces.",
        "source": "com.puppycrawl.tools.checkstyle.checks.regexp.RegexpSinglelineCheck"
    },
    {
        "line": "463",
        "severity": "error",
        "message": "Line has trailing spaces.",
        "source": "com.puppycrawl.tools.checkstyle.checks.regexp.RegexpSinglelineCheck"
    },
    {
        "line": "470",
        "severity": "error",
        "message": "Line has trailing spaces.",
        "source": "com.puppycrawl.tools.checkstyle.checks.regexp.RegexpSinglelineCheck"
    },
    {
        "line": "475",
        "severity": "error",
        "message": "Line has trailing spaces.",
        "source": "com.puppycrawl.tools.checkstyle.checks.regexp.RegexpSinglelineCheck"
    },
    {
        "line": "479",
        "severity": "error",
        "message": "Line has trailing spaces.",
        "source": "com.puppycrawl.tools.checkstyle.checks.regexp.RegexpSinglelineCheck"
    },
    {
        "line": "493",
        "severity": "error",
        "message": "Line has trailing spaces.",
        "source": "com.puppycrawl.tools.checkstyle.checks.regexp.RegexpSinglelineCheck"
    }
]