[
    {
        "line": "1",
        "severity": "error",
        "message": "Line does not match expected header line of '/\\*\\*\\**'.",
        "source": "com.puppycrawl.tools.checkstyle.checks.header.RegexpHeaderCheck"
    },
    {
        "line": "20",
        "column": "5",
        "severity": "error",
        "message": "Missing a Javadoc comment.",
        "source": "com.puppycrawl.tools.checkstyle.checks.javadoc.JavadocVariableCheck"
    },
    {
        "line": "22",
        "column": "5",
        "severity": "error",
        "message": "Missing a Javadoc comment.",
        "source": "com.puppycrawl.tools.checkstyle.checks.javadoc.JavadocVariableCheck"
    },
    {
        "line": "23",
        "column": "5",
        "severity": "error",
        "message": "Missing a Javadoc comment.",
        "source": "com.puppycrawl.tools.checkstyle.checks.javadoc.JavadocVariableCheck"
    },
    {
        "line": "25",
        "column": "5",
        "severity": "error",
        "message": "Missing a Javadoc comment.",
        "source": "com.puppycrawl.tools.checkstyle.checks.javadoc.JavadocVariableCheck"
    },
    {
        "line": "26",
        "column": "5",
        "severity": "error",
        "message": "Missing a Javadoc comment.",
        "source": "com.puppycrawl.tools.checkstyle.checks.javadoc.JavadocVariableCheck"
    },
    {
        "line": "27",
        "column": "5",
        "severity": "error",
        "message": "Missing a Javadoc comment.",
        "source": "com.puppycrawl.tools.checkstyle.checks.javadoc.JavadocVariableCheck"
    },
    {
        "line": "29",
        "column": "5",
        "severity": "error",
        "message": "Missing a Javadoc comment.",
        "source": "com.puppycrawl.tools.checkstyle.checks.javadoc.JavadocVariableCheck"
    },
    {
        "line": "30",
        "column": "5",
        "severity": "error",
        "message": "Missing a Javadoc comment.",
        "source": "com.puppycrawl.tools.checkstyle.checks.javadoc.JavadocVariableCheck"
    },
    {
        "line": "31",
        "column": "5",
        "severity": "error",
        "message": "Missing a Javadoc comment.",
        "source": "com.puppycrawl.tools.checkstyle.checks.javadoc.JavadocVariableCheck"
    },
    {
        "line": "32",
        "column": "5",
        "severity": "error",
        "message": "Missing a Javadoc comment.",
        "source": "com.puppycrawl.tools.checkstyle.checks.javadoc.JavadocVariableCheck"
    },
    {
        "line": "34",
        "column": "5",
        "severity": "error",
        "message": "Missing a Javadoc comment.",
        "source": "com.puppycrawl.tools.checkstyle.checks.javadoc.JavadocVariableCheck"
    },
    {
        "line": "35",
        "column": "5",
        "severity": "error",
        "message": "Missing a Javadoc comment.",
        "source": "com.puppycrawl.tools.checkstyle.checks.javadoc.JavadocVariableCheck"
    },
    {
        "line": "36",
        "column": "5",
        "severity": "error",
        "message": "Missing a Javadoc comment.",
        "source": "com.puppycrawl.tools.checkstyle.checks.javadoc.JavadocVariableCheck"
    },
    {
        "line": "38",
        "column": "5",
        "severity": "error",
        "message": "Missing a Javadoc comment.",
        "source": "com.puppycrawl.tools.checkstyle.checks.javadoc.JavadocVariableCheck"
    },
    {
        "line": "55",
        "severity": "error",
        "message": "'if' construct must use '{}'s.",
        "source": "com.puppycrawl.tools.checkstyle.checks.blocks.NeedBracesCheck"
    },
    {
        "line": "87",
        "severity": "error",
        "message": "'if' construct must use '{}'s.",
        "source": "com.puppycrawl.tools.checkstyle.checks.blocks.NeedBracesCheck"
    },
    {
        "line": "90",
        "severity": "error",
        "message": "'if' construct must use '{}'s.",
        "source": "com.puppycrawl.tools.checkstyle.checks.blocks.NeedBracesCheck"
    },
    {
        "line": "93",
        "severity": "error",
        "message": "'if' construct must use '{}'s.",
        "source": "com.puppycrawl.tools.checkstyle.checks.blocks.NeedBracesCheck"
    },
    {
        "line": "103",
        "severity": "error",
        "message": "'if' construct must use '{}'s.",
        "source": "com.puppycrawl.tools.checkstyle.checks.blocks.NeedBracesCheck"
    },
    {
        "line": "140",
        "severity": "error",
        "message": "'if' construct must use '{}'s.",
        "source": "com.puppycrawl.tools.checkstyle.checks.blocks.NeedBracesCheck"
    },
    {
        "line": "142",
        "severity": "error",
        "message": "'else' construct must use '{}'s.",
        "source": "com.puppycrawl.tools.checkstyle.checks.blocks.NeedBracesCheck"
    },
    {
        "line": "145",
        "severity": "error",
        "message": "'if' construct must use '{}'s.",
        "source": "com.puppycrawl.tools.checkstyle.checks.blocks.NeedBracesCheck"
    },
    {
        "line": "147",
        "severity": "error",
        "message": "'else' construct must use '{}'s.",
        "source": "com.puppycrawl.tools.checkstyle.checks.blocks.NeedBracesCheck"
    },
    {
        "line": "157",
        "severity": "error",
        "message": "'if' construct must use '{}'s.",
        "source": "com.puppycrawl.tools.checkstyle.checks.blocks.NeedBracesCheck"
    },
    {
        "line": "183",
        "severity": "error",
        "message": "'if' construct must use '{}'s.",
        "source": "com.puppycrawl.tools.checkstyle.checks.blocks.NeedBracesCheck"
    },
    {
        "line": "204",
        "severity": "error",
        "message": "'if' construct must use '{}'s.",
        "source": "com.puppycrawl.tools.checkstyle.checks.blocks.NeedBracesCheck"
    },
    {
        "line": "207",
        "severity": "error",
        "message": "'if' construct must use '{}'s.",
        "source": "com.puppycrawl.tools.checkstyle.checks.blocks.NeedBracesCheck"
    },
    {
        "line": "251",
        "severity": "error",
        "message": "'if' construct must use '{}'s.",
        "source": "com.puppycrawl.tools.checkstyle.checks.blocks.NeedBracesCheck"
    },
    {
        "line": "258",
        "severity": "error",
        "message": "'if' construct must use '{}'s.",
        "source": "com.puppycrawl.tools.checkstyle.checks.blocks.NeedBracesCheck"
    }
]