[
    {
        "line": "24",
        "severity": "error",
        "message": "Line has trailing spaces.",
        "source": "com.puppycrawl.tools.checkstyle.checks.regexp.RegexpSinglelineCheck"
    },
    {
        "line": "37",
        "column": "5",
        "severity": "error",
        "message": "Missing a Javadoc comment.",
        "source": "com.puppycrawl.tools.checkstyle.checks.javadoc.JavadocVariableCheck"
    },
    {
        "line": "39",
        "column": "12",
        "severity": "error",
        "message": "Redundant 'static' modifier.",
        "source": "com.puppycrawl.tools.checkstyle.checks.modifier.RedundantModifierCheck"
    },
    {
        "line": "60",
        "severity": "error",
        "message": "Must include both @java.lang.Deprecated annotation and @deprecated Javadoc tag with description.",
        "source": "com.puppycrawl.tools.checkstyle.checks.annotation.MissingDeprecatedCheck"
    },
    {
        "line": "70",
        "severity": "error",
        "message": "Must include both @java.lang.Deprecated annotation and @deprecated Javadoc tag with description.",
        "source": "com.puppycrawl.tools.checkstyle.checks.annotation.MissingDeprecatedCheck"
    }
]