[
    {
        "line": "48",
        "column": "13",
        "severity": "error",
        "message": "More than 7 parameters (found 9).",
        "source": "com.puppycrawl.tools.checkstyle.checks.sizes.ParameterNumberCheck"
    },
    {
        "line": "48",
        "column": "28",
        "severity": "error",
        "message": "Parameter requestURI should be final.",
        "source": "com.puppycrawl.tools.checkstyle.checks.FinalParametersCheck"
    },
    {
        "line": "48",
        "column": "44",
        "severity": "error",
        "message": "Parameter queryString should be final.",
        "source": "com.puppycrawl.tools.checkstyle.checks.FinalParametersCheck"
    },
    {
        "line": "48",
        "column": "64",
        "severity": "error",
        "message": "Parameter httpSession should be final.",
        "source": "com.puppycrawl.tools.checkstyle.checks.FinalParametersCheck"
    },
    {
        "line": "48",
        "column": "84",
        "severity": "error",
        "message": "Parameter secure should be final.",
        "source": "com.puppycrawl.tools.checkstyle.checks.FinalParametersCheck"
    },
    {
        "line": "48",
        "column": "100",
        "severity": "error",
        "message": "Parameter userPrincipal should be final.",
        "source": "com.puppycrawl.tools.checkstyle.checks.FinalParametersCheck"
    },
    {
        "line": "49",
        "column": "28",
        "severity": "error",
        "message": "Parameter IsUserInRoleDelegate should be final.",
        "source": "com.puppycrawl.tools.checkstyle.checks.FinalParametersCheck"
    },
    {
        "line": "49",
        "column": "57",
        "severity": "error",
        "message": "Name 'IsUserInRoleDelegate' must match pattern '^[a-z][a-zA-Z0-9]*$'.",
        "source": "com.puppycrawl.tools.checkstyle.checks.naming.ParameterNameCheck"
    },
    {
        "line": "49",
        "column": "79",
        "severity": "error",
        "message": "Parameter remoteAddr should be final.",
        "source": "com.puppycrawl.tools.checkstyle.checks.FinalParametersCheck"
    },
    {
        "line": "49",
        "column": "98",
        "severity": "error",
        "message": "Parameter parameterMap should be final.",
        "source": "com.puppycrawl.tools.checkstyle.checks.FinalParametersCheck"
    },
    {
        "line": "50",
        "column": "41",
        "severity": "error",
        "message": "Parameter headers should be final.",
        "source": "com.puppycrawl.tools.checkstyle.checks.FinalParametersCheck"
    },
    {
        "line": "83",
        "column": "29",
        "severity": "error",
        "message": "Parameter name should be final.",
        "source": "com.puppycrawl.tools.checkstyle.checks.FinalParametersCheck"
    },
    {
        "line": "122",
        "column": "33",
        "severity": "error",
        "message": "Parameter role should be final.",
        "source": "com.puppycrawl.tools.checkstyle.checks.FinalParametersCheck"
    },
    {
        "line": "195",
        "column": "38",
        "severity": "error",
        "message": "Parameter requestContext should be final.",
        "source": "com.puppycrawl.tools.checkstyle.checks.FinalParametersCheck"
    },
    {
        "line": "217",
        "column": "35",
        "severity": "error",
        "message": "Parameter requestURI should be final.",
        "source": "com.puppycrawl.tools.checkstyle.checks.FinalParametersCheck"
    },
    {
        "line": "217",
        "column": "39",
        "severity": "error",
        "message": "'requestURI' hides a field.",
        "source": "com.puppycrawl.tools.checkstyle.checks.coding.HiddenFieldCheck"
    },
    {
        "line": "228",
        "column": "36",
        "severity": "error",
        "message": "Parameter queryString should be final.",
        "source": "com.puppycrawl.tools.checkstyle.checks.FinalParametersCheck"
    },
    {
        "line": "228",
        "column": "43",
        "severity": "error",
        "message": "'queryString' hides a field.",
        "source": "com.puppycrawl.tools.checkstyle.checks.coding.HiddenFieldCheck"
    },
    {
        "line": "239",
        "column": "36",
        "severity": "error",
        "message": "Parameter httpSession should be final.",
        "source": "com.puppycrawl.tools.checkstyle.checks.FinalParametersCheck"
    },
    {
        "line": "239",
        "column": "43",
        "severity": "error",
        "message": "'httpSession' hides a field.",
        "source": "com.puppycrawl.tools.checkstyle.checks.coding.HiddenFieldCheck"
    },
    {
        "line": "250",
        "column": "31",
        "severity": "error",
        "message": "Parameter secure should be final.",
        "source": "com.puppycrawl.tools.checkstyle.checks.FinalParametersCheck"
    },
    {
        "line": "250",
        "column": "39",
        "severity": "error",
        "message": "'secure' hides a field.",
        "source": "com.puppycrawl.tools.checkstyle.checks.coding.HiddenFieldCheck"
    },
    {
        "line": "261",
        "column": "38",
        "severity": "error",
        "message": "Parameter principal should be final.",
        "source": "com.puppycrawl.tools.checkstyle.checks.FinalParametersCheck"
    },
    {
        "line": "272",
        "column": "45",
        "severity": "error",
        "message": "Parameter isUserInRoleDelegate should be final.",
        "source": "com.puppycrawl.tools.checkstyle.checks.FinalParametersCheck"
    },
    {
        "line": "272",
        "column": "66",
        "severity": "error",
        "message": "'isUserInRoleDelegate' hides a field.",
        "source": "com.puppycrawl.tools.checkstyle.checks.coding.HiddenFieldCheck"
    },
    {
        "line": "283",
        "column": "37",
        "severity": "error",
        "message": "Parameter parameterMap should be final.",
        "source": "com.puppycrawl.tools.checkstyle.checks.FinalParametersCheck"
    },
    {
        "line": "283",
        "column": "59",
        "severity": "error",
        "message": "'parameterMap' hides a field.",
        "source": "com.puppycrawl.tools.checkstyle.checks.coding.HiddenFieldCheck"
    },
    {
        "line": "302",
        "column": "35",
        "severity": "error",
        "message": "Parameter remoteAddr should be final.",
        "source": "com.puppycrawl.tools.checkstyle.checks.FinalParametersCheck"
    },
    {
        "line": "302",
        "column": "42",
        "severity": "error",
        "message": "'remoteAddr' hides a field.",
        "source": "com.puppycrawl.tools.checkstyle.checks.coding.HiddenFieldCheck"
    },
    {
        "line": "336",
        "column": "13",
        "severity": "error",
        "message": "Redundant 'public' modifier.",
        "source": "com.puppycrawl.tools.checkstyle.checks.modifier.RedundantModifierCheck"
    }
]